exputils/__init__.py
exputils/io.py
exputils/profile.py
exputils/random_seed_generator.py
exputils/data/__init__.py
exputils/data/confusion_matrix.py
exputils/data/confusion_tensor.py
exputils/data/labels.py
exputils/ml/__init__.py
exputils/ml/generic_predictors.py
exputils/ml/tensorboard.py
exputils/ray/__init__.py
exputils/visuals/__init__.py
exputils-0.1.6.dist-info/LICENSE.txt
exputils-0.1.6.dist-info/METADATA
exputils-0.1.6.dist-info/WHEEL
exputils-0.1.6.dist-info/top_level.txt
exputils-0.1.6.dist-info/RECORD
