Metadata-Version: 2.1
Name: exputils
Version: 0.1.6
Summary: Convenient functions that are commonly used for running machine learning experiments.
Home-page: https://github.com/prijatelj/exputils
Author: Derek S. Prijatelj
Author-email: dprijate@nd.edu
License: UNKNOWN
Platform: UNKNOWN
Classifier: Programming Language :: Python :: 3
Classifier: License :: OSI Approved :: MIT License
Classifier: Operating System :: OS Independent
Requires-Python: >=3.6
License-File: LICENSE.txt
Requires-Dist: bidict
Requires-Dist: h5py
Requires-Dist: packaging
Requires-Dist: pandas
Requires-Dist: plotly
Requires-Dist: numpy
Requires-Dist: scikit-learn (>=0.23)
Requires-Dist: sortedcollections
